MANIFEST.in
README.rst
setup.py
abce/__init__.py
abce/agent.py
abce/compile.py
abce/database.py
abce/db.py
abce/expiringgood.py
abce/goods.py
abce/group.py
abce/inventory.py
abce/messaging.py
abce/multiprocess.py
abce/notenoughgoods.py
abce/online_variance.c
abce/online_variance.py
abce/online_variance.pyx
abce/postbox.py
abce/postprocess.py
abce/quote.py
abce/show.py
abce/singleprocess.py
abce/trade.c
abce/trade.py
abce/trade.pyx
abce/webtext.py
abce.egg-info/PKG-INFO
abce.egg-info/SOURCES.txt
abce.egg-info/dependency_links.txt
abce.egg-info/requires.txt
abce.egg-info/top_level.txt
abce/agents/__init__.py
abce/agents/firm.py
abce/agents/household.py
abce/contracts/__init__.py
abce/contracts/contracting.py
abce/contracts/contracts.py
abce/contracts/flexiblecontracting.py
abce/gui/__init__.py
abce/gui/basiclayout.py
abce/gui/bokehwidget.py
abce/gui/dockpanel.py
abce/gui/form.py
abce/gui/loadform.py
abce/gui/make_graphs.py
abce/gui/webtext.py
unittest/aggregate_agent.csv
unittest/aggregate_friendly_agent.csv
unittest/aggregated_agent.csv
unittest/aggregated_friendly_agent.csv
unittest/ball.py
unittest/buy.py
unittest/buyexpiringcapital.py
unittest/contractbuyer.py
unittest/contractbuyerstop.py
unittest/contractseller.py
unittest/contractsellerstop.py
unittest/endowment.py
unittest/expiringcapital.py
unittest/give.py
unittest/giveexpiringcapital.py
unittest/killer.py
unittest/logger_test.py
unittest/messagea.py
unittest/messageb.py
unittest/panel_agent.csv
unittest/panel_friendly_agent.csv
unittest/production_multifirm.py
unittest/profile.sh
unittest/quote_buy.py
unittest/sell.py
unittest/start.py
unittest/start_agent_indexing.py
unittest/start_agent_numerical_indexing.py
unittest/start_combinable_actions.py
unittest/start_core_engine.py
unittest/start_custom_database.py
unittest/start_delete_create.py
unittest/start_individual_access.py
unittest/start_logging_friendly_names_test.py
unittest/start_logging_test.py
unittest/start_production_consumption.py
unittest/start_return.py
unittest/tools.py
unittest/utility_household.py
unittest/victim.py