Metadata-Version: 1.0
Name: abce
Version: 0.9.5b0
Summary: Agent-Based Complete Economy modelling platform
Home-page: https://github.com/AB-CE/abce.git
Author: Davoud Taghawi-Nejad
Author-email: Davoud@Taghawi-Nejad.de
License: UNKNOWN
Platform: UNKNOWN
